biomedical_data_generator/__init__.py
biomedical_data_generator/__main__.py
biomedical_data_generator/config.py
biomedical_data_generator/generator.py
biomedical_data_generator-0.1.3.dist-info/METADATA
biomedical_data_generator-0.1.3.dist-info/WHEEL
biomedical_data_generator-0.1.3.dist-info/entry_points.txt
biomedical_data_generator-0.1.3.dist-info/licenses/LICENSE
biomedical_data_generator-0.1.3.dist-info/RECORD
