Metadata-Version: 2.4
Name: biomedical-data-generator
Version: 0.1.3
Summary: Generate synthetic data for data science, machine learning, and statistics.
License: MIT
License-File: LICENSE
Keywords: artificial data,synthetic data,data generation,data simulation,data science,machine learning,statistics,data analysis
Author: Sigrun May
Author-email: s.may@ostfalia.de
Requires-Python: >=3.10,<4.0
Classifier: Development Status :: 4 - Beta
Classifier: Intended Audience :: Developers
Classifier: Intended Audience :: Education
Classifier: Intended Audience :: Science/Research
Classifier: License :: OSI Approved :: MIT License
Classifier: Operating System :: OS Independent
Classifier: Programming Language :: Python :: 3
Classifier: Programming Language :: Python :: 3.10
Classifier: Programming Language :: Python :: 3.11
Classifier: Programming Language :: Python :: 3.12
Classifier: Programming Language :: Python :: 3.13
Classifier: Programming Language :: Python :: 3.14
Classifier: Programming Language :: Python :: 3 :: Only
Classifier: Topic :: Scientific/Engineering
Classifier: Topic :: Scientific/Engineering :: Artificial Intelligence
Classifier: Topic :: Scientific/Engineering :: Mathematics
Classifier: Topic :: Software Development
Classifier: Topic :: Software Development :: Libraries
Classifier: Topic :: Software Development :: Libraries :: Python Modules
Requires-Dist: matplotlib
Requires-Dist: numpy (>=1.23)
Requires-Dist: pandas
Requires-Dist: pydantic (>=2.7,<3.0)
Requires-Dist: pyyaml
Requires-Dist: seaborn
Requires-Dist: statsmodels
Project-URL: Bug Tracker, https://github.com/sigrun-may/biomedical-data-generator/issues
Project-URL: Homepage, https://github.com/sigrun-may/biomedical-data-generator
